<?xml-model href="../../baudi-odd/rng/baudi_tei.rng" type="application/xml" schematypens="http://relaxng.org/ns/structure/1.0"?> <?xml-model href="../../baudi-odd/rng/baudi_tei.rng" type="application/xml" schematypens="http://purl.oclc.org/dsdl/schematron"?><person xmlns="http://www.tei-c.org/ns/1.0" xml:id="baudi-04-6c0f17c3" status="approved">
    <persName>
        <addName type="title">Professor</addName>
        <surname>Rüdel</surname>
    </persName>
    <sex type="male"/>
    <nationality key="de"/>
    <occupation>Dirigent</occupation>
</person>