<person xmlns="http://www.tei-c.org/ns/1.0" xml:id="baudi-04-950fbff3" status="proposed">
    <persName>
        <forename sort="1" type="used">Friederike</forename>
        <surname type="birth">Wenner</surname>
        <surname type="married" from="1859-11-15">Baumann</surname>
        <addName/>
    </persName>
    <birth when-iso="1835-03-01">
        <placeName>Mühlburg</placeName>
    </birth>
    <death/>
    <faith key="rk"/>
    <sex type="female"/>
    <nationality key="de"/>
    <note>1859-11-15 Hochzeit mit Ludwig Baumann in Eggenstein</note>
</person>