<?xml-model href="../../baudi-odd/rng/baudi_tei.rng" type="application/xml" schematypens="http://relaxng.org/ns/structure/1.0"?>
<?xml-model href="../../baudi-odd/rng/baudi_tei.rng" type="application/xml" schematypens="http://purl.oclc.org/dsdl/schematron"?>
<person xmlns="http://www.tei-c.org/ns/1.0" xml:id="baudi-04-16c61111" status="approved">
    <persName type="reg">
        <surname>Baumann</surname>, <forename>Ludwig</forename> <genName>Senior</genName>
    </persName>
    <persName type="full">
        <forename>Friedrich</forename>
        <forename>Ludwig</forename>
        <surname>Baumann</surname>
    </persName>
    <persName type="alt">
        <forename>Ludwig</forename>
        <surname>Baumann</surname>
    </persName>
    <birth when="1833-10-04">
        <placeName key="baudi-06-f383af0f">Muggensturm</placeName>
    </birth>
    <death when="1873"/>
    <faith key="ev"/>
    <sex type="male"/>
    <nationality key="de"/>
    <occupation>Wundarzneidiener (Chirurg)</occupation>
    <note>Hochzeit mit <persName key="baudi-04-950fbff3">Freiderike Wenner</persName> am <date when="1859-11-15">15. Nov. 1859</date> in <settlement key="baudi-06-ef212d55">Eggenstein</settlement></note>
</person>